{
  "generated_at": "2026-04-14 14:07:36",
  "items": [
    {
      "lat": 0.0,
      "lng": 0.0,
      "name": "",
      "address": "0",
      "updated": "2026-04-14 14:02:15",
      "weight": 20,
      "count": 2
    },
    {
      "lat": 34.926842,
      "lng": 135.759281,
      "name": "",
      "address": "",
      "updated": "2026-04-14 14:02:15",
      "weight": 3,
      "count": 1
    },
    {
      "lat": 34.932852,
      "lng": 135.766828,
      "name": "",
      "address": "",
      "updated": "2026-04-14 14:02:15",
      "weight": 1,
      "count": 1
    },
    {
      "lat": 34.939134,
      "lng": 135.752229,
      "name": "",
      "address": "",
      "updated": "2026-04-14 14:02:15",
      "weight": 2,
      "count": 2
    },
    {
      "lat": 34.939783,
      "lng": 135.765245,
      "name": "",
      "address": "",
      "updated": "2026-04-14 14:02:15",
      "weight": 1,
      "count": 1
    },
    {
      "lat": 34.94218,
      "lng": 135.75286,
      "name": "",
      "address": "",
      "updated": "2026-04-14 14:02:15",
      "weight": 1,
      "count": 1
    },
    {
      "lat": 34.94912,
      "lng": 135.752227,
      "name": "",
      "address": "",
      "updated": "2026-04-14 14:02:15",
      "weight": 1,
      "count": 1
    },
    {
      "lat": 34.952058,
      "lng": 135.749416,
      "name": "",
      "address": "",
      "updated": "2026-04-14 14:02:15",
      "weight": 3,
      "count": 1
    },
    {
      "lat": 34.954109,
      "lng": 135.765578,
      "name": "",
      "address": "",
      "updated": "2026-04-14 14:02:15",
      "weight": 1,
      "count": 1
    },
    {
      "lat": 34.955721,
      "lng": 135.755765,
      "name": "",
      "address": "",
      "updated": "2026-04-14 14:02:15",
      "weight": 1,
      "count": 1
    },
    {
      "lat": 34.955807,
      "lng": 135.77004,
      "name": "",
      "address": "",
      "updated": "2026-04-14 14:02:15",
      "weight": 1,
      "count": 1
    },
    {
      "lat": 34.962999,
      "lng": 135.767028,
      "name": "",
      "address": "",
      "updated": "2026-04-14 14:02:15",
      "weight": 1,
      "count": 1
    },
    {
      "lat": 34.963534,
      "lng": 135.759901,
      "name": "",
      "address": "",
      "updated": "2026-04-14 14:02:15",
      "weight": 6,
      "count": 2
    },
    {
      "lat": 34.963625,
      "lng": 135.709925,
      "name": "",
      "address": "",
      "updated": "2026-04-14 14:02:15",
      "weight": 1,
      "count": 1
    },
    {
      "lat": 34.9676593,
      "lng": 135.7685435,
      "name": "",
      "address": "",
      "updated": "2026-04-14 14:02:15",
      "weight": 5,
      "count": 1
    },
    {
      "lat": 34.967825,
      "lng": 135.768361,
      "name": "",
      "address": "",
      "updated": "2026-04-14 14:02:15",
      "weight": 1,
      "count": 1
    },
    {
      "lat": 34.968352,
      "lng": 135.732613,
      "name": "",
      "address": "",
      "updated": "2026-04-14 14:02:15",
      "weight": 1,
      "count": 1
    },
    {
      "lat": 34.973535,
      "lng": 135.752371,
      "name": "",
      "address": "",
      "updated": "2026-04-14 14:02:15",
      "weight": 1,
      "count": 1
    },
    {
      "lat": 34.975584,
      "lng": 135.728015,
      "name": "",
      "address": "",
      "updated": "2026-04-14 14:02:15",
      "weight": 1,
      "count": 1
    },
    {
      "lat": 34.976024,
      "lng": 135.754825,
      "name": "",
      "address": "",
      "updated": "2026-04-14 14:02:15",
      "weight": 1,
      "count": 1
    },
    {
      "lat": 34.978533,
      "lng": 135.702391,
      "name": "",
      "address": "",
      "updated": "2026-04-14 14:02:15",
      "weight": 4,
      "count": 2
    },
    {
      "lat": 34.978916,
      "lng": 135.71161,
      "name": "",
      "address": "",
      "updated": "2026-04-14 14:02:15",
      "weight": 5,
      "count": 1
    },
    {
      "lat": 34.979557,
      "lng": 135.766438,
      "name": "",
      "address": "",
      "updated": "2026-04-14 14:02:15",
      "weight": 1,
      "count": 1
    },
    {
      "lat": 34.981326,
      "lng": 135.76001,
      "name": "",
      "address": "",
      "updated": "2026-04-14 14:02:15",
      "weight": 1,
      "count": 1
    },
    {
      "lat": 34.983039,
      "lng": 135.756857,
      "name": "",
      "address": "",
      "updated": "2026-04-14 14:02:15",
      "weight": 1,
      "count": 1
    },
    {
      "lat": 34.98305,
      "lng": 135.774,
      "name": "",
      "address": "",
      "updated": "2026-04-14 14:02:15",
      "weight": 1,
      "count": 1
    },
    {
      "lat": 34.983828,
      "lng": 135.740408,
      "name": "",
      "address": "",
      "updated": "2026-04-14 14:02:15",
      "weight": 5,
      "count": 1
    },
    {
      "lat": 34.987757,
      "lng": 135.762593,
      "name": "",
      "address": "",
      "updated": "2026-04-14 14:02:15",
      "weight": 1,
      "count": 1
    },
    {
      "lat": 34.98839,
      "lng": 135.756081,
      "name": "",
      "address": "",
      "updated": "2026-04-14 14:02:15",
      "weight": 4,
      "count": 2
    },
    {
      "lat": 34.989067,
      "lng": 135.735744,
      "name": "",
      "address": "",
      "updated": "2026-04-14 14:02:15",
      "weight": 1,
      "count": 1
    },
    {
      "lat": 34.989307,
      "lng": 135.777088,
      "name": "",
      "address": "",
      "updated": "2026-04-14 14:02:15",
      "weight": 2,
      "count": 2
    },
    {
      "lat": 34.989662,
      "lng": 135.692873,
      "name": "",
      "address": "",
      "updated": "2026-04-14 14:02:15",
      "weight": 1,
      "count": 1
    },
    {
      "lat": 34.990338,
      "lng": 135.740378,
      "name": "",
      "address": "",
      "updated": "2026-04-14 14:02:15",
      "weight": 5,
      "count": 1
    },
    {
      "lat": 34.990631,
      "lng": 135.718694,
      "name": "",
      "address": "",
      "updated": "2026-04-14 14:02:15",
      "weight": 1,
      "count": 1
    },
    {
      "lat": 34.991347,
      "lng": 135.720384,
      "name": "",
      "address": "",
      "updated": "2026-04-14 14:02:15",
      "weight": 1,
      "count": 1
    },
    {
      "lat": 34.991663,
      "lng": 135.723603,
      "name": "",
      "address": "",
      "updated": "2026-04-14 14:02:15",
      "weight": 1,
      "count": 1
    },
    {
      "lat": 34.991794,
      "lng": 135.777699,
      "name": "",
      "address": "",
      "updated": "2026-04-14 14:02:15",
      "weight": 1,
      "count": 1
    },
    {
      "lat": 34.992113,
      "lng": 135.728511,
      "name": "",
      "address": "",
      "updated": "2026-04-14 14:02:15",
      "weight": 3,
      "count": 1
    },
    {
      "lat": 34.992705,
      "lng": 135.767653,
      "name": "",
      "address": "",
      "updated": "2026-04-14 14:02:15",
      "weight": 1,
      "count": 1
    },
    {
      "lat": 34.994841,
      "lng": 135.715236,
      "name": "",
      "address": "",
      "updated": "2026-04-14 14:02:15",
      "weight": 1,
      "count": 1
    },
    {
      "lat": 34.995231,
      "lng": 135.736602,
      "name": "",
      "address": "",
      "updated": "2026-04-14 14:02:15",
      "weight": 1,
      "count": 1
    },
    {
      "lat": 34.995664,
      "lng": 135.732011,
      "name": "",
      "address": "",
      "updated": "2026-04-14 14:02:15",
      "weight": 6,
      "count": 2
    },
    {
      "lat": 34.995664,
      "lng": 135.742471,
      "name": "",
      "address": "",
      "updated": "2026-04-14 14:02:15",
      "weight": 1,
      "count": 1
    },
    {
      "lat": 34.995803,
      "lng": 135.738592,
      "name": "",
      "address": "",
      "updated": "2026-04-14 14:02:15",
      "weight": 1,
      "count": 1
    },
    {
      "lat": 34.996543,
      "lng": 135.766228,
      "name": "",
      "address": "",
      "updated": "2026-04-14 14:02:15",
      "weight": 1,
      "count": 1
    },
    {
      "lat": 34.996565,
      "lng": 135.765853,
      "name": "",
      "address": "",
      "updated": "2026-04-14 14:02:15",
      "weight": 10,
      "count": 1
    },
    {
      "lat": 34.996653,
      "lng": 135.757399,
      "name": "",
      "address": "",
      "updated": "2026-04-14 14:02:15",
      "weight": 1,
      "count": 1
    },
    {
      "lat": 34.997362,
      "lng": 135.774566,
      "name": "",
      "address": "",
      "updated": "2026-04-14 14:02:15",
      "weight": 1,
      "count": 1
    },
    {
      "lat": 34.997974,
      "lng": 135.777325,
      "name": "",
      "address": "",
      "updated": "2026-04-14 14:02:15",
      "weight": 3,
      "count": 1
    },
    {
      "lat": 34.99974,
      "lng": 135.775593,
      "name": "",
      "address": "",
      "updated": "2026-04-14 14:02:15",
      "weight": 1,
      "count": 1
    },
    {
      "lat": 35.000857,
      "lng": 135.77535,
      "name": "",
      "address": "",
      "updated": "2026-04-14 14:02:15",
      "weight": 1,
      "count": 1
    },
    {
      "lat": 35.001139,
      "lng": 135.749175,
      "name": "",
      "address": "",
      "updated": "2026-04-14 14:02:15",
      "weight": 1,
      "count": 1
    },
    {
      "lat": 35.001272,
      "lng": 135.716511,
      "name": "",
      "address": "",
      "updated": "2026-04-14 14:02:15",
      "weight": 1,
      "count": 1
    },
    {
      "lat": 35.003201,
      "lng": 135.764049,
      "name": "",
      "address": "",
      "updated": "2026-04-14 14:02:15",
      "weight": 1,
      "count": 1
    },
    {
      "lat": 35.003291,
      "lng": 135.77293,
      "name": "",
      "address": "",
      "updated": "2026-04-14 14:02:15",
      "weight": 1,
      "count": 1
    },
    {
      "lat": 35.00357,
      "lng": 135.725647,
      "name": "",
      "address": "",
      "updated": "2026-04-14 14:02:15",
      "weight": 1,
      "count": 1
    },
    {
      "lat": 35.003797,
      "lng": 135.706254,
      "name": "",
      "address": "",
      "updated": "2026-04-14 14:02:15",
      "weight": 3,
      "count": 1
    },
    {
      "lat": 35.006043,
      "lng": 135.7589,
      "name": "",
      "address": "",
      "updated": "2026-04-14 14:02:15",
      "weight": 2,
      "count": 2
    },
    {
      "lat": 35.006956,
      "lng": 135.682461,
      "name": "",
      "address": "",
      "updated": "2026-04-14 14:02:15",
      "weight": 4,
      "count": 2
    },
    {
      "lat": 35.007587,
      "lng": 135.75371,
      "name": "",
      "address": "",
      "updated": "2026-04-14 14:02:15",
      "weight": 1,
      "count": 1
    },
    {
      "lat": 35.008241,
      "lng": 135.682063,
      "name": "",
      "address": "",
      "updated": "2026-04-14 14:02:15",
      "weight": 1,
      "count": 1
    },
    {
      "lat": 35.00846,
      "lng": 135.720982,
      "name": "",
      "address": "",
      "updated": "2026-04-14 14:02:15",
      "weight": 1,
      "count": 1
    },
    {
      "lat": 35.008707,
      "lng": 135.760415,
      "name": "",
      "address": "",
      "updated": "2026-04-14 14:02:15",
      "weight": 1,
      "count": 1
    },
    {
      "lat": 35.008748,
      "lng": 135.755785,
      "name": "",
      "address": "",
      "updated": "2026-04-14 14:02:15",
      "weight": 5,
      "count": 1
    },
    {
      "lat": 35.00978,
      "lng": 135.7831,
      "name": "",
      "address": "",
      "updated": "2026-04-14 14:02:15",
      "weight": 5,
      "count": 1
    },
    {
      "lat": 35.009798,
      "lng": 135.749163,
      "name": "",
      "address": "",
      "updated": "2026-04-14 14:02:15",
      "weight": 1,
      "count": 1
    },
    {
      "lat": 35.010073,
      "lng": 135.763813,
      "name": "",
      "address": "",
      "updated": "2026-04-14 14:02:15",
      "weight": 1,
      "count": 1
    },
    {
      "lat": 35.010612,
      "lng": 135.741602,
      "name": "",
      "address": "",
      "updated": "2026-04-14 14:02:15",
      "weight": 1,
      "count": 1
    },
    {
      "lat": 35.010999,
      "lng": 135.750601,
      "name": "",
      "address": "",
      "updated": "2026-04-14 14:02:15",
      "weight": 1,
      "count": 1
    },
    {
      "lat": 35.011803,
      "lng": 135.77784,
      "name": "",
      "address": "",
      "updated": "2026-04-14 14:02:15",
      "weight": 1,
      "count": 1
    },
    {
      "lat": 35.012211,
      "lng": 135.731695,
      "name": "",
      "address": "",
      "updated": "2026-04-14 14:02:15",
      "weight": 1,
      "count": 1
    },
    {
      "lat": 35.01381,
      "lng": 135.705311,
      "name": "",
      "address": "",
      "updated": "2026-04-14 14:02:15",
      "weight": 1,
      "count": 1
    },
    {
      "lat": 35.014326,
      "lng": 135.755075,
      "name": "",
      "address": "",
      "updated": "2026-04-14 14:02:15",
      "weight": 5,
      "count": 1
    },
    {
      "lat": 35.014457,
      "lng": 135.76878,
      "name": "",
      "address": "",
      "updated": "2026-04-14 14:02:15",
      "weight": 1,
      "count": 1
    },
    {
      "lat": 35.014807,
      "lng": 135.762428,
      "name": "",
      "address": "",
      "updated": "2026-04-14 14:02:15",
      "weight": 1,
      "count": 1
    },
    {
      "lat": 35.015196,
      "lng": 135.694181,
      "name": "",
      "address": "",
      "updated": "2026-04-14 14:02:15",
      "weight": 5,
      "count": 1
    },
    {
      "lat": 35.015209,
      "lng": 135.770077,
      "name": "",
      "address": "",
      "updated": "2026-04-14 14:02:15",
      "weight": 1,
      "count": 1
    },
    {
      "lat": 35.015246,
      "lng": 135.742394,
      "name": "",
      "address": "",
      "updated": "2026-04-14 14:02:15",
      "weight": 1,
      "count": 1
    },
    {
      "lat": 35.015415,
      "lng": 135.757936,
      "name": "",
      "address": "",
      "updated": "2026-04-14 14:02:15",
      "weight": 1,
      "count": 1
    },
    {
      "lat": 35.01563,
      "lng": 135.721795,
      "name": "",
      "address": "",
      "updated": "2026-04-14 14:02:15",
      "weight": 1,
      "count": 1
    },
    {
      "lat": 35.016019,
      "lng": 135.777611,
      "name": "",
      "address": "",
      "updated": "2026-04-14 14:02:15",
      "weight": 1,
      "count": 1
    },
    {
      "lat": 35.017586,
      "lng": 135.748204,
      "name": "",
      "address": "",
      "updated": "2026-04-14 14:02:15",
      "weight": 1,
      "count": 1
    },
    {
      "lat": 35.017986,
      "lng": 135.786944,
      "name": "",
      "address": "",
      "updated": "2026-04-14 14:02:15",
      "weight": 3,
      "count": 1
    },
    {
      "lat": 35.018776,
      "lng": 135.729547,
      "name": "",
      "address": "",
      "updated": "2026-04-14 14:02:15",
      "weight": 1,
      "count": 1
    },
    {
      "lat": 35.021524,
      "lng": 135.770661,
      "name": "",
      "address": "",
      "updated": "2026-04-14 14:02:15",
      "weight": 1,
      "count": 1
    },
    {
      "lat": 35.023946,
      "lng": 135.767389,
      "name": "",
      "address": "",
      "updated": "2026-04-14 14:02:15",
      "weight": 1,
      "count": 1
    },
    {
      "lat": 35.024783,
      "lng": 135.752157,
      "name": "",
      "address": "",
      "updated": "2026-04-14 14:02:15",
      "weight": 1,
      "count": 1
    },
    {
      "lat": 35.026384,
      "lng": 135.74559,
      "name": "",
      "address": "",
      "updated": "2026-04-14 14:02:15",
      "weight": 5,
      "count": 1
    },
    {
      "lat": 35.027279,
      "lng": 135.699926,
      "name": "",
      "address": "",
      "updated": "2026-04-14 14:02:15",
      "weight": 1,
      "count": 1
    },
    {
      "lat": 35.027961,
      "lng": 135.775012,
      "name": "",
      "address": "",
      "updated": "2026-04-14 14:02:15",
      "weight": 1,
      "count": 1
    },
    {
      "lat": 35.028094,
      "lng": 135.746804,
      "name": "",
      "address": "",
      "updated": "2026-04-14 14:02:15",
      "weight": 5,
      "count": 1
    },
    {
      "lat": 35.028541,
      "lng": 135.755926,
      "name": "",
      "address": "",
      "updated": "2026-04-14 14:02:15",
      "weight": 3,
      "count": 1
    },
    {
      "lat": 35.028788,
      "lng": 135.709703,
      "name": "",
      "address": "",
      "updated": "2026-04-14 14:02:15",
      "weight": 5,
      "count": 1
    },
    {
      "lat": 35.02903,
      "lng": 135.723865,
      "name": "",
      "address": "",
      "updated": "2026-04-14 14:02:15",
      "weight": 1,
      "count": 1
    },
    {
      "lat": 35.029362,
      "lng": 135.777633,
      "name": "",
      "address": "",
      "updated": "2026-04-14 14:02:15",
      "weight": 4,
      "count": 2
    },
    {
      "lat": 35.02943,
      "lng": 135.754135,
      "name": "",
      "address": "",
      "updated": "2026-04-14 14:02:15",
      "weight": 5,
      "count": 1
    },
    {
      "lat": 35.029858,
      "lng": 135.758798,
      "name": "",
      "address": "",
      "updated": "2026-04-14 14:02:15",
      "weight": 1,
      "count": 1
    },
    {
      "lat": 35.030386,
      "lng": 135.773047,
      "name": "",
      "address": "",
      "updated": "2026-04-14 14:02:15",
      "weight": 1,
      "count": 1
    },
    {
      "lat": 35.031057,
      "lng": 135.737721,
      "name": "",
      "address": "",
      "updated": "2026-04-14 14:02:15",
      "weight": 1,
      "count": 1
    },
    {
      "lat": 35.034603,
      "lng": 135.726487,
      "name": "",
      "address": "",
      "updated": "2026-04-14 14:02:15",
      "weight": 4,
      "count": 2
    },
    {
      "lat": 35.042922,
      "lng": 135.748563,
      "name": "",
      "address": "",
      "updated": "2026-04-14 14:02:15",
      "weight": 5,
      "count": 1
    },
    {
      "lat": 35.044143,
      "lng": 135.737766,
      "name": "",
      "address": "",
      "updated": "2026-04-14 14:02:15",
      "weight": 1,
      "count": 1
    },
    {
      "lat": 35.045932,
      "lng": 135.788399,
      "name": "",
      "address": "",
      "updated": "2026-04-14 14:02:15",
      "weight": 1,
      "count": 1
    },
    {
      "lat": 35.05162,
      "lng": 135.745368,
      "name": "",
      "address": "",
      "updated": "2026-04-14 14:02:15",
      "weight": 4,
      "count": 2
    },
    {
      "lat": 35.052506,
      "lng": 135.7925,
      "name": "",
      "address": "",
      "updated": "2026-04-14 14:02:15",
      "weight": 3,
      "count": 1
    },
    {
      "lat": 35.057452,
      "lng": 135.741036,
      "name": "",
      "address": "",
      "updated": "2026-04-14 14:02:15",
      "weight": 1,
      "count": 1
    },
    {
      "lat": 35.05777,
      "lng": 135.751753,
      "name": "",
      "address": "",
      "updated": "2026-04-14 14:02:15",
      "weight": 3,
      "count": 1
    },
    {
      "lat": 35.063442,
      "lng": 135.750075,
      "name": "",
      "address": "",
      "updated": "2026-04-14 14:02:15",
      "weight": 2,
      "count": 2
    },
    {
      "lat": 35.064392,
      "lng": 135.785563,
      "name": "",
      "address": "",
      "updated": "2026-04-14 14:02:15",
      "weight": 1,
      "count": 1
    },
    {
      "lat": 35.065204,
      "lng": 135.780946,
      "name": "",
      "address": "",
      "updated": "2026-04-14 14:02:15",
      "weight": 3,
      "count": 1
    },
    {
      "lat": 35.065974,
      "lng": 135.776034,
      "name": "",
      "address": "",
      "updated": "2026-04-14 14:02:15",
      "weight": 1,
      "count": 1
    },
    {
      "lat": 35.069895,
      "lng": 135.750138,
      "name": "",
      "address": "",
      "updated": "2026-04-14 14:02:15",
      "weight": 1,
      "count": 1
    },
    {
      "lat": 35.071658,
      "lng": 135.756302,
      "name": "",
      "address": "",
      "updated": "2026-04-14 14:02:15",
      "weight": 5,
      "count": 1
    },
    {
      "lat": 35.071979,
      "lng": 135.769666,
      "name": "",
      "address": "",
      "updated": "2026-04-14 14:02:15",
      "weight": 3,
      "count": 3
    }
  ]
}